{
    "/js/app.js": "/js/app.js",
    "/css/app.css": "/css/app.css",
    "/0.7cd5a7b9b081cdd828d0.hot-update.js": "/0.7cd5a7b9b081cdd828d0.hot-update.js",
    "/0.bd05c5edcc362935c46e.hot-update.js": "/0.bd05c5edcc362935c46e.hot-update.js",
    "/0.83a2a69f241a2a64b221.hot-update.js": "/0.83a2a69f241a2a64b221.hot-update.js",
    "/0.ff2f8b191161a4504892.hot-update.js": "/0.ff2f8b191161a4504892.hot-update.js",
    "/0.883486ef8a23e9ccba22.hot-update.js": "/0.883486ef8a23e9ccba22.hot-update.js",
    "/0.ffd573b947a525e790d0.hot-update.js": "/0.ffd573b947a525e790d0.hot-update.js",
    "/0.53ac144a6b42dcdd7e18.hot-update.js": "/0.53ac144a6b42dcdd7e18.hot-update.js",
    "/0.82b6cf40da0f20e0685b.hot-update.js": "/0.82b6cf40da0f20e0685b.hot-update.js",
    "/0.4286ba5060501e4f52ed.hot-update.js": "/0.4286ba5060501e4f52ed.hot-update.js",
    "/0.fd9efdda690c3b8bd8a8.hot-update.js": "/0.fd9efdda690c3b8bd8a8.hot-update.js",
    "/0.834ab1652ffd489ce6e8.hot-update.js": "/0.834ab1652ffd489ce6e8.hot-update.js",
    "/0.db4ce6cc2d6ce9cc32d9.hot-update.js": "/0.db4ce6cc2d6ce9cc32d9.hot-update.js",
    "/0.86475a964b1fce56f49e.hot-update.js": "/0.86475a964b1fce56f49e.hot-update.js",
    "/0.929fc23cbcd61b89ca2f.hot-update.js": "/0.929fc23cbcd61b89ca2f.hot-update.js",
    "/0.281aa66bec8d47adfa39.hot-update.js": "/0.281aa66bec8d47adfa39.hot-update.js",
    "/0.8bff2fb4f580d330ecf9.hot-update.js": "/0.8bff2fb4f580d330ecf9.hot-update.js",
    "/0.3f11a3136b30e3e183f8.hot-update.js": "/0.3f11a3136b30e3e183f8.hot-update.js",
    "/0.b69826bf3c674c5da638.hot-update.js": "/0.b69826bf3c674c5da638.hot-update.js",
    "/0.a38914fcccec5559ab42.hot-update.js": "/0.a38914fcccec5559ab42.hot-update.js",
    "/0.d8ff848cd3b7657549e0.hot-update.js": "/0.d8ff848cd3b7657549e0.hot-update.js",
    "/0.4f0b1508d9a10d860f85.hot-update.js": "/0.4f0b1508d9a10d860f85.hot-update.js",
    "/0.8633d9128fe664e53040.hot-update.js": "/0.8633d9128fe664e53040.hot-update.js",
    "/0.288e4ce2959b0f8f3774.hot-update.js": "/0.288e4ce2959b0f8f3774.hot-update.js",
    "/0.a1845d8b7486fc3bb4c5.hot-update.js": "/0.a1845d8b7486fc3bb4c5.hot-update.js",
    "/0.4bf66e8cbbb5f4cad643.hot-update.js": "/0.4bf66e8cbbb5f4cad643.hot-update.js",
    "/0.78475ce7281392b8e2ad.hot-update.js": "/0.78475ce7281392b8e2ad.hot-update.js",
    "/0.230674ca99732020685c.hot-update.js": "/0.230674ca99732020685c.hot-update.js",
    "/0.73bd386193edca2a9db0.hot-update.js": "/0.73bd386193edca2a9db0.hot-update.js",
    "/0.3753fe5fef5f92f6ec37.hot-update.js": "/0.3753fe5fef5f92f6ec37.hot-update.js",
    "/0.71651e34623bb6ebc933.hot-update.js": "/0.71651e34623bb6ebc933.hot-update.js",
    "/0.c6fee67be664c82f44e9.hot-update.js": "/0.c6fee67be664c82f44e9.hot-update.js",
    "/0.c56fbb9bf76b1ed234d3.hot-update.js": "/0.c56fbb9bf76b1ed234d3.hot-update.js",
    "/0.c260b482ab3ff180c4de.hot-update.js": "/0.c260b482ab3ff180c4de.hot-update.js",
    "/0.c1c3cfc18f9c957f0004.hot-update.js": "/0.c1c3cfc18f9c957f0004.hot-update.js",
    "/0.a19eacabc44bcf47532c.hot-update.js": "/0.a19eacabc44bcf47532c.hot-update.js",
    "/0.1ef699576ae47f1ce24c.hot-update.js": "/0.1ef699576ae47f1ce24c.hot-update.js",
    "/0.aac5b109abd4b2f6bb84.hot-update.js": "/0.aac5b109abd4b2f6bb84.hot-update.js",
    "/0.8e163d5e159733b84b06.hot-update.js": "/0.8e163d5e159733b84b06.hot-update.js",
    "/0.c356b4b451cff7f2eb4e.hot-update.js": "/0.c356b4b451cff7f2eb4e.hot-update.js",
    "/0.284e1cb1877d5dbdecbe.hot-update.js": "/0.284e1cb1877d5dbdecbe.hot-update.js",
    "/0.eacf6fa5555962782d55.hot-update.js": "/0.eacf6fa5555962782d55.hot-update.js",
    "/0.d68431bdd508c1a46624.hot-update.js": "/0.d68431bdd508c1a46624.hot-update.js",
    "/0.0369a6e8b18abf6e5c83.hot-update.js": "/0.0369a6e8b18abf6e5c83.hot-update.js",
    "/0.0d1e5c3a40291d6e09f5.hot-update.js": "/0.0d1e5c3a40291d6e09f5.hot-update.js",
    "/0.aef04fbfe11bccf53c73.hot-update.js": "/0.aef04fbfe11bccf53c73.hot-update.js",
    "/0.e83b62fb4479c710027a.hot-update.js": "/0.e83b62fb4479c710027a.hot-update.js",
    "/0.c271c7b7fa017b2ea343.hot-update.js": "/0.c271c7b7fa017b2ea343.hot-update.js",
    "/0.aec0d80c2226eee73e30.hot-update.js": "/0.aec0d80c2226eee73e30.hot-update.js",
    "/0.9a216e2eee72a731d2a7.hot-update.js": "/0.9a216e2eee72a731d2a7.hot-update.js",
    "/0.1c1df030dc140b35b02d.hot-update.js": "/0.1c1df030dc140b35b02d.hot-update.js",
    "/0.3f8994ab084e64578115.hot-update.js": "/0.3f8994ab084e64578115.hot-update.js",
    "/0.915a1f39024e97afd320.hot-update.js": "/0.915a1f39024e97afd320.hot-update.js",
    "/0.7ca3d7ef1ff225984c11.hot-update.js": "/0.7ca3d7ef1ff225984c11.hot-update.js",
    "/0.59f770db907ee9edd116.hot-update.js": "/0.59f770db907ee9edd116.hot-update.js",
    "/0.ca599365826f7cf05937.hot-update.js": "/0.ca599365826f7cf05937.hot-update.js",
    "/0.eaa3c9209494e61fa95c.hot-update.js": "/0.eaa3c9209494e61fa95c.hot-update.js",
    "/0.3268058269d65a0d0a70.hot-update.js": "/0.3268058269d65a0d0a70.hot-update.js",
    "/0.8fe59052c6ed2d20a2e6.hot-update.js": "/0.8fe59052c6ed2d20a2e6.hot-update.js",
    "/0.788f38de565c5aee2fc8.hot-update.js": "/0.788f38de565c5aee2fc8.hot-update.js",
    "/0.13092cc8002386180c22.hot-update.js": "/0.13092cc8002386180c22.hot-update.js",
    "/0.16c2d89822e3f0508532.hot-update.js": "/0.16c2d89822e3f0508532.hot-update.js",
    "/0.212fed2eae91727e9a6d.hot-update.js": "/0.212fed2eae91727e9a6d.hot-update.js",
    "/0.51c7b77721bc58da4786.hot-update.js": "/0.51c7b77721bc58da4786.hot-update.js",
    "/0.71adfe40a36df268df89.hot-update.js": "/0.71adfe40a36df268df89.hot-update.js",
    "/0.abec139e24608dadb7e5.hot-update.js": "/0.abec139e24608dadb7e5.hot-update.js",
    "/0.af11f007260c650beb3d.hot-update.js": "/0.af11f007260c650beb3d.hot-update.js",
    "/0.acc951c03b5fa365f5a9.hot-update.js": "/0.acc951c03b5fa365f5a9.hot-update.js",
    "/0.37f2a7a9eb508038dfb7.hot-update.js": "/0.37f2a7a9eb508038dfb7.hot-update.js",
    "/0.37870c8846457ad455a7.hot-update.js": "/0.37870c8846457ad455a7.hot-update.js",
    "/0.4accf8f0a4834eb7dec2.hot-update.js": "/0.4accf8f0a4834eb7dec2.hot-update.js",
    "/0.0e16306dfc80e36b01fe.hot-update.js": "/0.0e16306dfc80e36b01fe.hot-update.js",
    "/0.314f3f39579d64e0eed0.hot-update.js": "/0.314f3f39579d64e0eed0.hot-update.js",
    "/0.87e32a45115de803ff37.hot-update.js": "/0.87e32a45115de803ff37.hot-update.js",
    "/0.b1a94ebf905fc9e47815.hot-update.js": "/0.b1a94ebf905fc9e47815.hot-update.js",
    "/0.e5fca38fc6175a36d716.hot-update.js": "/0.e5fca38fc6175a36d716.hot-update.js",
    "/0.a5f7298aefe54fd4f327.hot-update.js": "/0.a5f7298aefe54fd4f327.hot-update.js",
    "/0.1bdd25e3b46afd4a615c.hot-update.js": "/0.1bdd25e3b46afd4a615c.hot-update.js",
    "/0.3805de743d86680e9c90.hot-update.js": "/0.3805de743d86680e9c90.hot-update.js",
    "/0.50999de77547953819b9.hot-update.js": "/0.50999de77547953819b9.hot-update.js",
    "/0.19b5ac607ff45df7ea81.hot-update.js": "/0.19b5ac607ff45df7ea81.hot-update.js",
    "/0.561244cd38138c3d7046.hot-update.js": "/0.561244cd38138c3d7046.hot-update.js",
    "/0.9c07d2fb2cdc1a53c21e.hot-update.js": "/0.9c07d2fb2cdc1a53c21e.hot-update.js",
    "/0.889517ab3800e0ad5877.hot-update.js": "/0.889517ab3800e0ad5877.hot-update.js",
    "/0.559c8fe9400fba079483.hot-update.js": "/0.559c8fe9400fba079483.hot-update.js",
    "/0.136f5174ae7d118a297e.hot-update.js": "/0.136f5174ae7d118a297e.hot-update.js",
    "/0.3e8dc6c6c699e302ac9a.hot-update.js": "/0.3e8dc6c6c699e302ac9a.hot-update.js",
    "/0.ef37f333ce1e37862bb4.hot-update.js": "/0.ef37f333ce1e37862bb4.hot-update.js",
    "/0.a8ab2deb44ed9dd4c098.hot-update.js": "/0.a8ab2deb44ed9dd4c098.hot-update.js",
    "/0.5eda5b4b6aac70e18509.hot-update.js": "/0.5eda5b4b6aac70e18509.hot-update.js",
    "/0.41524a9f710c1ea7c44b.hot-update.js": "/0.41524a9f710c1ea7c44b.hot-update.js",
    "/0.cc53a542ec9d366bb0eb.hot-update.js": "/0.cc53a542ec9d366bb0eb.hot-update.js",
    "/0.0ce8927c8c5ed6527b02.hot-update.js": "/0.0ce8927c8c5ed6527b02.hot-update.js",
    "/0.b65837cc6b31115e7297.hot-update.js": "/0.b65837cc6b31115e7297.hot-update.js",
    "/0.5fc1c128954d1d9239b0.hot-update.js": "/0.5fc1c128954d1d9239b0.hot-update.js",
    "/0.6f8172c76bd38774a04b.hot-update.js": "/0.6f8172c76bd38774a04b.hot-update.js",
    "/0.4ddab83f509980d17eb5.hot-update.js": "/0.4ddab83f509980d17eb5.hot-update.js",
    "/0.93b7e4ab5561a55f2ca4.hot-update.js": "/0.93b7e4ab5561a55f2ca4.hot-update.js",
    "/0.df62a3e8b97651c67c05.hot-update.js": "/0.df62a3e8b97651c67c05.hot-update.js",
    "/0.542470e759b31b9be99b.hot-update.js": "/0.542470e759b31b9be99b.hot-update.js",
    "/0.25af6edb473443f30345.hot-update.js": "/0.25af6edb473443f30345.hot-update.js",
    "/0.6bfe408e8b704d972b7e.hot-update.js": "/0.6bfe408e8b704d972b7e.hot-update.js",
    "/0.76f488ef9938dd8ec76f.hot-update.js": "/0.76f488ef9938dd8ec76f.hot-update.js",
    "/0.75f02a2bac5016c7516a.hot-update.js": "/0.75f02a2bac5016c7516a.hot-update.js",
    "/0.b0323d82fa60231ce86c.hot-update.js": "/0.b0323d82fa60231ce86c.hot-update.js",
    "/0.8882614244c9fe845bb6.hot-update.js": "/0.8882614244c9fe845bb6.hot-update.js",
    "/0.441ba3cf7ad6e299c313.hot-update.js": "/0.441ba3cf7ad6e299c313.hot-update.js",
    "/0.c6e7b1f57b89e2c7afb1.hot-update.js": "/0.c6e7b1f57b89e2c7afb1.hot-update.js",
    "/0.97d8437353435b4129d8.hot-update.js": "/0.97d8437353435b4129d8.hot-update.js",
    "/0.365f6cc9f052f63957ce.hot-update.js": "/0.365f6cc9f052f63957ce.hot-update.js"
}